pynbcache/__init__.py
pynbcache/cache.py
pynbcache/persistence.py
pynbcache-0.1.0.dist-info/LICENSE
pynbcache-0.1.0.dist-info/WHEEL
pynbcache-0.1.0.dist-info/METADATA
pynbcache-0.1.0.dist-info/RECORD
